<?xml version="1.0" encoding="utf-8"?>
<clothing-items>
 <clothing>
  <id>
   428322592
  </id>
  <name>
   Adidas T-shirt N-7073
  </name>
  <category>
   T-shirt
  </category>
  <size>
   M
  </size>
  <color>
   Фиолетовый
  </color>
  <material>
   Полиэстер
  </material>
  <price>
   596882
  </price>
  <rating>
   4.45
  </rating>
  <reviews>
   83320
  </reviews>
  <new>
   +
  </new>
  <exclusive>
   no
  </exclusive>
  <sporty>
   yes
  </sporty>
 </clothing>
 <clothing>
  <id>
   817456566
  </id>
  <name>
   Vans Gloves R-2925
  </name>
  <category>
   Gloves
  </category>
  <size>
   XL
  </size>
  <color>
   Красный
  </color>
  <material>
   Нейлон
  </material>
  <price>
   524960
  </price>
  <rating>
   3.04
  </rating>
  <reviews>
   198206
  </reviews>
  <new>
   -
  </new>
  <sporty>
   no
  </sporty>
 </clothing>
 <clothing>
  <id>
   654828828
  </id>
  <name>
   Reebok Hat W-5598
  </name>
  <category>
   Hat
  </category>
  <size>
   S
  </size>
  <color>
   Голубой
  </color>
  <material>
   Лен
  </material>
  <price>
   824286
  </price>
  <rating>
   2.14
  </rating>
  <reviews>
   432096
  </reviews>
  <new>
   -
  </new>
  <exclusive>
   yes
  </exclusive>
 </clothing>
 <clothing>
  <id>
   874490551
  </id>
  <name>
   Adidas Pants R-4657
  </name>
  <category>
   Pants
  </category>
  <size>
   S
  </size>
  <color>
   Оранжевый
  </color>
  <material>
   Шерсть
  </material>
  <price>
   283773
  </price>
  <rating>
   1.59
  </rating>
  <reviews>
   757611
  </reviews>
  <exclusive>
   no
  </exclusive>
  <sporty>
   yes
  </sporty>
 </clothing>
 <clothing>
  <id>
   496127601
  </id>
  <name>
   Vans Skirt A-5433
  </name>
  <category>
   Skirt
  </category>
  <size>
   L
  </size>
  <color>
   Желтый
  </color>
  <material>
   Шелк
  </material>
  <price>
   615525
  </price>
  <rating>
   1.16
  </rating>
  <reviews>
   300868
  </reviews>
  <new>
   -
  </new>
  <exclusive>
   no
  </exclusive>
  <sporty>
   yes
  </sporty>
 </clothing>
 <clothing>
  <id>
   911054098
  </id>
  <name>
   Fila Umbrellas S-5520
  </name>
  <category>
   Umbrellas
  </category>
  <size>
   XXL
  </size>
  <color>
   Оранжевый
  </color>
  <material>
   Лен
  </material>
  <price>
   676916
  </price>
  <rating>
   1.05
  </rating>
  <reviews>
   355322
  </reviews>
  <exclusive>
   no
  </exclusive>
  <sporty>
   no
  </sporty>
 </clothing>
 <clothing>
  <id>
   434515726
  </id>
  <name>
   PleinSport Socks U-8670
  </name>
  <category>
   Socks
  </category>
  <size>
   S
  </size>
  <color>
   Зеленый
  </color>
  <material>
   Кожа
  </material>
  <price>
   886283
  </price>
  <rating>
   4.72
  </rating>
  <reviews>
   744500
  </reviews>
  <new>
   -
  </new>
 </clothing>
 <clothing>
  <id>
   177733369
  </id>
  <name>
   Addidas Skirt O-1633
  </name>
  <category>
   Skirt
  </category>
  <size>
   L
  </size>
  <color>
   Красный
  </color>
  <material>
   Кожа
  </material>
  <price>
   198788
  </price>
  <rating>
   2.01
  </rating>
  <reviews>
   592210
  </reviews>
  <sporty>
   no
  </sporty>
 </clothing>
 <clothing>
  <id>
   870066871
  </id>
  <name>
   Adidas Socks T-8606
  </name>
  <category>
   Socks
  </category>
  <size>
   M
  </size>
  <color>
   Фиолетовый
  </color>
  <material>
   Шелк
  </material>
  <price>
   958715
  </price>
  <rating>
   1.39
  </rating>
  <reviews>
   862861
  </reviews>
  <new>
   -
  </new>
  <sporty>
   no
  </sporty>
 </clothing>
 <clothing>
  <id>
   319499860
  </id>
  <name>
   Nike Skirt D-7150
  </name>
  <category>
   Skirt
  </category>
  <size>
   L
  </size>
  <color>
   Голубой
  </color>
  <material>
   Лен
  </material>
  <price>
   539023
  </price>
  <rating>
   2.27
  </rating>
  <reviews>
   288197
  </reviews>
 </clothing>
 <clothing>
  <id>
   133914733
  </id>
  <name>
   DC Umbrellas P-6178
  </name>
  <category>
   Umbrellas
  </category>
  <size>
   XL
  </size>
  <color>
   Голубой
  </color>
  <material>
   Кожа
  </material>
  <price>
   310129
  </price>
  <rating>
   4.73
  </rating>
  <reviews>
   993158
  </reviews>
  <sporty>
   no
  </sporty>
 </clothing>
 <clothing>
  <id>
   271237684
  </id>
  <name>
   Ellesse Jeans Q-5252
  </name>
  <category>
   Jeans
  </category>
  <size>
   XL
  </size>
  <color>
   Желтый
  </color>
  <material>
   Вискоза
  </material>
  <price>
   257776
  </price>
  <rating>
   4.83
  </rating>
  <reviews>
   178079
  </reviews>
  <sporty>
   no
  </sporty>
 </clothing>
 <clothing>
  <id>
   605094002
  </id>
  <name>
   Adidas Gloves Q-5014
  </name>
  <category>
   Gloves
  </category>
  <size>
   XL
  </size>
  <color>
   Желтый
  </color>
  <material>
   Нейлон
  </material>
  <price>
   365810
  </price>
  <rating>
   3.0
  </rating>
  <reviews>
   314324
  </reviews>
  <exclusive>
   yes
  </exclusive>
  <sporty>
   yes
  </sporty>
 </clothing>
 <clothing>
  <id>
   388996103
  </id>
  <name>
   Lacoste Skirt V-7114
  </name>
  <category>
   Skirt
  </category>
  <size>
   M
  </size>
  <color>
   Голубой
  </color>
  <material>
   Полиэстер
  </material>
  <price>
   274591
  </price>
  <rating>
   4.57
  </rating>
  <reviews>
   939447
  </reviews>
 </clothing>
 <clothing>
  <id>
   289372434
  </id>
  <name>
   Lacoste Jacket Q-4571
  </name>
  <category>
   Jacket
  </category>
  <size>
   XL
  </size>
  <color>
   Желтый
  </color>
  <material>
   Кожа
  </material>
  <price>
   222598
  </price>
  <rating>
   4.8
  </rating>
  <reviews>
   221446
  </reviews>
  <exclusive>
   yes
  </exclusive>
 </clothing>
 <clothing>
  <id>
   759940557
  </id>
  <name>
   Puma Handbags W-6808
  </name>
  <category>
   Handbags
  </category>
  <size>
   L
  </size>
  <color>
   Оранжевый
  </color>
  <material>
   Кожа
  </material>
  <price>
   813660
  </price>
  <rating>
   2.97
  </rating>
  <reviews>
   353970
  </reviews>
  <sporty>
   no
  </sporty>
 </clothing>
 <clothing>
  <id>
   520835403
  </id>
  <name>
   Reebok Dress Q-4364
  </name>
  <category>
   Dress
  </category>
  <size>
   XL
  </size>
  <color>
   Зеленый
  </color>
  <material>
   Хлопок
  </material>
  <price>
   110327
  </price>
  <rating>
   2.37
  </rating>
  <reviews>
   675899
  </reviews>
  <exclusive>
   no
  </exclusive>
  <sporty>
   yes
  </sporty>
 </clothing>
 <clothing>
  <id>
   300087305
  </id>
  <name>
   Converse Belts I-3511
  </name>
  <category>
   Belts
  </category>
  <size>
   M
  </size>
  <color>
   Желтый
  </color>
  <material>
   Хлопок
  </material>
  <price>
   205048
  </price>
  <rating>
   4.14
  </rating>
  <reviews>
   636512
  </reviews>
  <sporty>
   yes
  </sporty>
 </clothing>
 <clothing>
  <id>
   651847541
  </id>
  <name>
   Fila Pants V-7897
  </name>
  <category>
   Pants
  </category>
  <size>
   XXL
  </size>
  <color>
   Голубой
  </color>
  <material>
   Лен
  </material>
  <price>
   116241
  </price>
  <rating>
   2.64
  </rating>
  <reviews>
   562193
  </reviews>
  <new>
   -
  </new>
  <sporty>
   yes
  </sporty>
 </clothing>
 <clothing>
  <id>
   521380768
  </id>
  <name>
   Reebok Jeans C-7962
  </name>
  <category>
   Jeans
  </category>
  <size>
   M
  </size>
  <color>
   Желтый
  </color>
  <material>
   Кожа
  </material>
  <price>
   256818
  </price>
  <rating>
   3.66
  </rating>
  <reviews>
   81732
  </reviews>
  <new>
   -
  </new>
  <sporty>
   no
  </sporty>
 </clothing>
 <clothing>
  <id>
   701676191
  </id>
  <name>
   DC Belts J-8543
  </name>
  <category>
   Belts
  </category>
  <size>
   XXL
  </size>
  <color>
   Желтый
  </color>
  <material>
   Лен
  </material>
  <price>
   588065
  </price>
  <rating>
   4.42
  </rating>
  <reviews>
   516026
  </reviews>
  <new>
   -
  </new>
  <exclusive>
   no
  </exclusive>
  <sporty>
   no
  </sporty>
 </clothing>
</clothing-items>
