<?xml version="1.0" encoding="utf-8"?>
<clothing-items>
 <clothing>
  <id>
   601910151
  </id>
  <name>
   Addidas Socks X-6514
  </name>
  <category>
   Socks
  </category>
  <size>
   M
  </size>
  <color>
   Голубой
  </color>
  <material>
   Шерсть
  </material>
  <price>
   561995
  </price>
  <rating>
   1.1
  </rating>
  <reviews>
   947770
  </reviews>
  <sporty>
   no
  </sporty>
 </clothing>
 <clothing>
  <id>
   851231083
  </id>
  <name>
   Ellesse Umbrellas G-4030
  </name>
  <category>
   Umbrellas
  </category>
  <size>
   XXL
  </size>
  <color>
   Красный
  </color>
  <material>
   Полиэстер
  </material>
  <price>
   224705
  </price>
  <rating>
   4.15
  </rating>
  <reviews>
   828298
  </reviews>
  <new>
   -
  </new>
  <sporty>
   no
  </sporty>
 </clothing>
 <clothing>
  <id>
   949609033
  </id>
  <name>
   Puma Shoes R-4306
  </name>
  <category>
   Shoes
  </category>
  <size>
   M
  </size>
  <color>
   Оранжевый
  </color>
  <material>
   Нейлон
  </material>
  <price>
   453301
  </price>
  <rating>
   2.25
  </rating>
  <reviews>
   986191
  </reviews>
  <new>
   -
  </new>
  <exclusive>
   no
  </exclusive>
  <sporty>
   no
  </sporty>
 </clothing>
 <clothing>
  <id>
   537962091
  </id>
  <name>
   Converse Gloves F-7840
  </name>
  <category>
   Gloves
  </category>
  <size>
   L
  </size>
  <color>
   Красный
  </color>
  <material>
   Шерсть
  </material>
  <price>
   723556
  </price>
  <rating>
   2.1
  </rating>
  <reviews>
   32669
  </reviews>
  <exclusive>
   yes
  </exclusive>
  <sporty>
   no
  </sporty>
 </clothing>
 <clothing>
  <id>
   206712967
  </id>
  <name>
   Reebok Socks L-9566
  </name>
  <category>
   Socks
  </category>
  <size>
   S
  </size>
  <color>
   Зеленый
  </color>
  <material>
   Лен
  </material>
  <price>
   112844
  </price>
  <rating>
   2.76
  </rating>
  <reviews>
   391503
  </reviews>
  <exclusive>
   yes
  </exclusive>
 </clothing>
 <clothing>
  <id>
   607886298
  </id>
  <name>
   DC Shirt C-9567
  </name>
  <category>
   Shirt
  </category>
  <size>
   XL
  </size>
  <color>
   Голубой
  </color>
  <material>
   Кожа
  </material>
  <price>
   220493
  </price>
  <rating>
   2.85
  </rating>
  <reviews>
   398624
  </reviews>
  <exclusive>
   no
  </exclusive>
 </clothing>
 <clothing>
  <id>
   767942184
  </id>
  <name>
   New Balance Skirt R-5286
  </name>
  <category>
   Skirt
  </category>
  <size>
   XXL
  </size>
  <color>
   Синий
  </color>
  <material>
   Нейлон
  </material>
  <price>
   161372
  </price>
  <rating>
   3.68
  </rating>
  <reviews>
   926551
  </reviews>
  <sporty>
   no
  </sporty>
 </clothing>
 <clothing>
  <id>
   711263723
  </id>
  <name>
   Asics Blouse R-5945
  </name>
  <category>
   Blouse
  </category>
  <size>
   XL
  </size>
  <color>
   Красный
  </color>
  <material>
   Шерсть
  </material>
  <price>
   877731
  </price>
  <rating>
   3.07
  </rating>
  <reviews>
   967047
  </reviews>
  <new>
   -
  </new>
  <sporty>
   yes
  </sporty>
 </clothing>
 <clothing>
  <id>
   862075764
  </id>
  <name>
   Puma Handbags Q-8944
  </name>
  <category>
   Handbags
  </category>
  <size>
   M
  </size>
  <color>
   Оранжевый
  </color>
  <material>
   Лен
  </material>
  <price>
   719751
  </price>
  <rating>
   2.32
  </rating>
  <reviews>
   727302
  </reviews>
 </clothing>
 <clothing>
  <id>
   242233544
  </id>
  <name>
   Reebok T-shirt V-8518
  </name>
  <category>
   T-shirt
  </category>
  <size>
   L
  </size>
  <color>
   Оранжевый
  </color>
  <material>
   Полиэстер
  </material>
  <price>
   764513
  </price>
  <rating>
   1.38
  </rating>
  <reviews>
   555398
  </reviews>
  <exclusive>
   no
  </exclusive>
 </clothing>
 <clothing>
  <id>
   767175594
  </id>
  <name>
   Converse Umbrellas H-3952
  </name>
  <category>
   Umbrellas
  </category>
  <size>
   XL
  </size>
  <color>
   Оранжевый
  </color>
  <material>
   Кожа
  </material>
  <price>
   246251
  </price>
  <rating>
   2.21
  </rating>
  <reviews>
   176947
  </reviews>
 </clothing>
 <clothing>
  <id>
   689942143
  </id>
  <name>
   Lacoste Pants Q-1777
  </name>
  <category>
   Pants
  </category>
  <size>
   S
  </size>
  <color>
   Желтый
  </color>
  <material>
   Лен
  </material>
  <price>
   957635
  </price>
  <rating>
   3.71
  </rating>
  <reviews>
   744926
  </reviews>
  <new>
   +
  </new>
  <exclusive>
   no
  </exclusive>
  <sporty>
   no
  </sporty>
 </clothing>
 <clothing>
  <id>
   633168100
  </id>
  <name>
   Nike Hat M-6686
  </name>
  <category>
   Hat
  </category>
  <size>
   L
  </size>
  <color>
   Голубой
  </color>
  <material>
   Вискоза
  </material>
  <price>
   195460
  </price>
  <rating>
   4.4
  </rating>
  <reviews>
   194595
  </reviews>
  <new>
   +
  </new>
  <exclusive>
   no
  </exclusive>
  <sporty>
   no
  </sporty>
 </clothing>
 <clothing>
  <id>
   461544416
  </id>
  <name>
   PleinSport Umbrellas U-4703
  </name>
  <category>
   Umbrellas
  </category>
  <size>
   XL
  </size>
  <color>
   Красный
  </color>
  <material>
   Хлопок
  </material>
  <price>
   177835
  </price>
  <rating>
   3.37
  </rating>
  <reviews>
   564415
  </reviews>
  <exclusive>
   no
  </exclusive>
  <sporty>
   no
  </sporty>
 </clothing>
 <clothing>
  <id>
   980007166
  </id>
  <name>
   Lacoste Jeans I-3863
  </name>
  <category>
   Jeans
  </category>
  <size>
   M
  </size>
  <color>
   Желтый
  </color>
  <material>
   Нейлон
  </material>
  <price>
   116642
  </price>
  <rating>
   3.55
  </rating>
  <reviews>
   642959
  </reviews>
  <new>
   -
  </new>
  <exclusive>
   no
  </exclusive>
 </clothing>
 <clothing>
  <id>
   828215266
  </id>
  <name>
   PleinSport Pants K-4506
  </name>
  <category>
   Pants
  </category>
  <size>
   M
  </size>
  <color>
   Голубой
  </color>
  <material>
   Нейлон
  </material>
  <price>
   499322
  </price>
  <rating>
   2.95
  </rating>
  <reviews>
   158945
  </reviews>
  <exclusive>
   yes
  </exclusive>
  <sporty>
   yes
  </sporty>
 </clothing>
 <clothing>
  <id>
   230557568
  </id>
  <name>
   Fila Dress Z-9783
  </name>
  <category>
   Dress
  </category>
  <size>
   L
  </size>
  <color>
   Голубой
  </color>
  <material>
   Шелк
  </material>
  <price>
   483659
  </price>
  <rating>
   3.46
  </rating>
  <reviews>
   503733
  </reviews>
  <exclusive>
   no
  </exclusive>
  <sporty>
   no
  </sporty>
 </clothing>
 <clothing>
  <id>
   519481536
  </id>
  <name>
   PleinSport Jacket J-8954
  </name>
  <category>
   Jacket
  </category>
  <size>
   L
  </size>
  <color>
   Голубой
  </color>
  <material>
   Кожа
  </material>
  <price>
   918036
  </price>
  <rating>
   1.96
  </rating>
  <reviews>
   684226
  </reviews>
  <sporty>
   no
  </sporty>
 </clothing>
 <clothing>
  <id>
   348503150
  </id>
  <name>
   Ellesse Umbrellas J-8910
  </name>
  <category>
   Umbrellas
  </category>
  <size>
   XXL
  </size>
  <color>
   Фиолетовый
  </color>
  <material>
   Лен
  </material>
  <price>
   442274
  </price>
  <rating>
   4.27
  </rating>
  <reviews>
   479236
  </reviews>
  <sporty>
   no
  </sporty>
 </clothing>
 <clothing>
  <id>
   778889010
  </id>
  <name>
   Asics Skirt X-8169
  </name>
  <category>
   Skirt
  </category>
  <size>
   L
  </size>
  <color>
   Фиолетовый
  </color>
  <material>
   Полиэстер
  </material>
  <price>
   723882
  </price>
  <rating>
   3.6
  </rating>
  <reviews>
   552425
  </reviews>
  <new>
   -
  </new>
 </clothing>
 <clothing>
  <id>
   889627558
  </id>
  <name>
   PleinSport Dress X-9328
  </name>
  <category>
   Dress
  </category>
  <size>
   XXL
  </size>
  <color>
   Желтый
  </color>
  <material>
   Шелк
  </material>
  <price>
   484832
  </price>
  <rating>
   4.14
  </rating>
  <reviews>
   123392
  </reviews>
  <new>
   -
  </new>
  <exclusive>
   no
  </exclusive>
  <sporty>
   no
  </sporty>
 </clothing>
 <clothing>
  <id>
   553531860
  </id>
  <name>
   Puma Jacket M-1539
  </name>
  <category>
   Jacket
  </category>
  <size>
   M
  </size>
  <color>
   Красный
  </color>
  <material>
   Лен
  </material>
  <price>
   898953
  </price>
  <rating>
   2.1
  </rating>
  <reviews>
   956167
  </reviews>
  <new>
   -
  </new>
  <exclusive>
   no
  </exclusive>
  <sporty>
   no
  </sporty>
 </clothing>
 <clothing>
  <id>
   164582167
  </id>
  <name>
   Addidas Shoes J-5148
  </name>
  <category>
   Shoes
  </category>
  <size>
   XL
  </size>
  <color>
   Зеленый
  </color>
  <material>
   Полиэстер
  </material>
  <price>
   403003
  </price>
  <rating>
   3.32
  </rating>
  <reviews>
   219109
  </reviews>
  <new>
   +
  </new>
  <sporty>
   yes
  </sporty>
 </clothing>
 <clothing>
  <id>
   218699275
  </id>
  <name>
   Reebok Shoes K-2962
  </name>
  <category>
   Shoes
  </category>
  <size>
   M
  </size>
  <color>
   Оранжевый
  </color>
  <material>
   Кожа
  </material>
  <price>
   338654
  </price>
  <rating>
   2.69
  </rating>
  <reviews>
   26777
  </reviews>
  <new>
   -
  </new>
  <exclusive>
   no
  </exclusive>
  <sporty>
   no
  </sporty>
 </clothing>
 <clothing>
  <id>
   212698084
  </id>
  <name>
   Fila Handbags W-2182
  </name>
  <category>
   Handbags
  </category>
  <size>
   M
  </size>
  <color>
   Синий
  </color>
  <material>
   Хлопок
  </material>
  <price>
   646117
  </price>
  <rating>
   2.48
  </rating>
  <reviews>
   733292
  </reviews>
  <new>
   -
  </new>
  <exclusive>
   no
  </exclusive>
  <sporty>
   yes
  </sporty>
 </clothing>
 <clothing>
  <id>
   332789152
  </id>
  <name>
   Addidas Pants E-7462
  </name>
  <category>
   Pants
  </category>
  <size>
   L
  </size>
  <color>
   Синий
  </color>
  <material>
   Кожа
  </material>
  <price>
   577177
  </price>
  <rating>
   2.3
  </rating>
  <reviews>
   787356
  </reviews>
  <new>
   -
  </new>
  <exclusive>
   no
  </exclusive>
  <sporty>
   yes
  </sporty>
 </clothing>
</clothing-items>
