<?xml version="1.0" encoding="utf-8"?>
<clothing-items>
 <clothing>
  <id>
   470812111
  </id>
  <name>
   Brooks Gloves N-7232
  </name>
  <category>
   Gloves
  </category>
  <size>
   XL
  </size>
  <color>
   Оранжевый
  </color>
  <material>
   Шерсть
  </material>
  <price>
   146040
  </price>
  <rating>
   3.19
  </rating>
  <reviews>
   46162
  </reviews>
  <new>
   -
  </new>
  <exclusive>
   no
  </exclusive>
  <sporty>
   yes
  </sporty>
 </clothing>
 <clothing>
  <id>
   595797871
  </id>
  <name>
   Fila Belts B-9698
  </name>
  <category>
   Belts
  </category>
  <size>
   M
  </size>
  <color>
   Фиолетовый
  </color>
  <material>
   Шерсть
  </material>
  <price>
   169412
  </price>
  <rating>
   2.99
  </rating>
  <reviews>
   82192
  </reviews>
  <new>
   +
  </new>
  <exclusive>
   yes
  </exclusive>
  <sporty>
   no
  </sporty>
 </clothing>
 <clothing>
  <id>
   598097733
  </id>
  <name>
   New Balance T-shirt V-3106
  </name>
  <category>
   T-shirt
  </category>
  <size>
   M
  </size>
  <color>
   Красный
  </color>
  <material>
   Хлопок
  </material>
  <price>
   883056
  </price>
  <rating>
   2.84
  </rating>
  <reviews>
   150541
  </reviews>
  <new>
   +
  </new>
  <sporty>
   no
  </sporty>
 </clothing>
 <clothing>
  <id>
   628732571
  </id>
  <name>
   Vans Belts X-3826
  </name>
  <category>
   Belts
  </category>
  <size>
   XL
  </size>
  <color>
   Желтый
  </color>
  <material>
   Нейлон
  </material>
  <price>
   172019
  </price>
  <rating>
   3.73
  </rating>
  <reviews>
   819882
  </reviews>
  <new>
   -
  </new>
  <exclusive>
   yes
  </exclusive>
 </clothing>
 <clothing>
  <id>
   813023146
  </id>
  <name>
   Lacoste Dress M-1088
  </name>
  <category>
   Dress
  </category>
  <size>
   XXL
  </size>
  <color>
   Синий
  </color>
  <material>
   Хлопок
  </material>
  <price>
   231543
  </price>
  <rating>
   3.01
  </rating>
  <reviews>
   418402
  </reviews>
  <new>
   -
  </new>
  <exclusive>
   yes
  </exclusive>
  <sporty>
   no
  </sporty>
 </clothing>
 <clothing>
  <id>
   692899153
  </id>
  <name>
   PleinSport Sweater H-6542
  </name>
  <category>
   Sweater
  </category>
  <size>
   XL
  </size>
  <color>
   Желтый
  </color>
  <material>
   Вискоза
  </material>
  <price>
   616298
  </price>
  <rating>
   4.65
  </rating>
  <reviews>
   820114
  </reviews>
  <exclusive>
   yes
  </exclusive>
  <sporty>
   yes
  </sporty>
 </clothing>
 <clothing>
  <id>
   302876049
  </id>
  <name>
   Asics Gloves T-7655
  </name>
  <category>
   Gloves
  </category>
  <size>
   L
  </size>
  <color>
   Зеленый
  </color>
  <material>
   Шелк
  </material>
  <price>
   720033
  </price>
  <rating>
   4.39
  </rating>
  <reviews>
   298798
  </reviews>
  <new>
   +
  </new>
  <exclusive>
   no
  </exclusive>
  <sporty>
   yes
  </sporty>
 </clothing>
 <clothing>
  <id>
   925686259
  </id>
  <name>
   Converse Pants L-7936
  </name>
  <category>
   Pants
  </category>
  <size>
   S
  </size>
  <color>
   Фиолетовый
  </color>
  <material>
   Вискоза
  </material>
  <price>
   901390
  </price>
  <rating>
   1.55
  </rating>
  <reviews>
   729595
  </reviews>
  <exclusive>
   yes
  </exclusive>
 </clothing>
 <clothing>
  <id>
   438454168
  </id>
  <name>
   Addidas Hat Y-8392
  </name>
  <category>
   Hat
  </category>
  <size>
   L
  </size>
  <color>
   Желтый
  </color>
  <material>
   Хлопок
  </material>
  <price>
   419657
  </price>
  <rating>
   1.25
  </rating>
  <reviews>
   201028
  </reviews>
  <new>
   +
  </new>
  <exclusive>
   no
  </exclusive>
  <sporty>
   yes
  </sporty>
 </clothing>
 <clothing>
  <id>
   933871463
  </id>
  <name>
   Puma Shirt K-2386
  </name>
  <category>
   Shirt
  </category>
  <size>
   S
  </size>
  <color>
   Желтый
  </color>
  <material>
   Шелк
  </material>
  <price>
   925902
  </price>
  <rating>
   1.72
  </rating>
  <reviews>
   475666
  </reviews>
  <new>
   -
  </new>
  <exclusive>
   no
  </exclusive>
  <sporty>
   yes
  </sporty>
 </clothing>
 <clothing>
  <id>
   465635099
  </id>
  <name>
   New Balance Shoes H-1428
  </name>
  <category>
   Shoes
  </category>
  <size>
   M
  </size>
  <color>
   Зеленый
  </color>
  <material>
   Хлопок
  </material>
  <price>
   437998
  </price>
  <rating>
   2.28
  </rating>
  <reviews>
   733839
  </reviews>
  <new>
   -
  </new>
 </clothing>
 <clothing>
  <id>
   156952557
  </id>
  <name>
   New Balance Handbags A-7719
  </name>
  <category>
   Handbags
  </category>
  <size>
   XXL
  </size>
  <color>
   Голубой
  </color>
  <material>
   Полиэстер
  </material>
  <price>
   261384
  </price>
  <rating>
   2.98
  </rating>
  <reviews>
   973745
  </reviews>
  <new>
   -
  </new>
  <exclusive>
   yes
  </exclusive>
  <sporty>
   no
  </sporty>
 </clothing>
 <clothing>
  <id>
   846548022
  </id>
  <name>
   Lacoste Umbrellas Q-2898
  </name>
  <category>
   Umbrellas
  </category>
  <size>
   S
  </size>
  <color>
   Зеленый
  </color>
  <material>
   Лен
  </material>
  <price>
   909211
  </price>
  <rating>
   3.73
  </rating>
  <reviews>
   580244
  </reviews>
  <new>
   -
  </new>
 </clothing>
 <clothing>
  <id>
   116515874
  </id>
  <name>
   Reebok Belts L-9855
  </name>
  <category>
   Belts
  </category>
  <size>
   S
  </size>
  <color>
   Зеленый
  </color>
  <material>
   Лен
  </material>
  <price>
   279959
  </price>
  <rating>
   3.66
  </rating>
  <reviews>
   34997
  </reviews>
  <exclusive>
   yes
  </exclusive>
 </clothing>
 <clothing>
  <id>
   511626890
  </id>
  <name>
   Asics Sweater S-7134
  </name>
  <category>
   Sweater
  </category>
  <size>
   XL
  </size>
  <color>
   Зеленый
  </color>
  <material>
   Вискоза
  </material>
  <price>
   597306
  </price>
  <rating>
   1.58
  </rating>
  <reviews>
   812679
  </reviews>
  <new>
   -
  </new>
 </clothing>
 <clothing>
  <id>
   135003224
  </id>
  <name>
   Vans Handbags W-9684
  </name>
  <category>
   Handbags
  </category>
  <size>
   S
  </size>
  <color>
   Фиолетовый
  </color>
  <material>
   Вискоза
  </material>
  <price>
   105494
  </price>
  <rating>
   2.98
  </rating>
  <reviews>
   155021
  </reviews>
  <exclusive>
   no
  </exclusive>
  <sporty>
   yes
  </sporty>
 </clothing>
 <clothing>
  <id>
   620084947
  </id>
  <name>
   Under Armour Umbrellas C-7613
  </name>
  <category>
   Umbrellas
  </category>
  <size>
   M
  </size>
  <color>
   Фиолетовый
  </color>
  <material>
   Кожа
  </material>
  <price>
   545662
  </price>
  <rating>
   3.41
  </rating>
  <reviews>
   921699
  </reviews>
  <new>
   -
  </new>
  <exclusive>
   yes
  </exclusive>
 </clothing>
 <clothing>
  <id>
   176549312
  </id>
  <name>
   Lacoste Shoes D-1235
  </name>
  <category>
   Shoes
  </category>
  <size>
   XL
  </size>
  <color>
   Зеленый
  </color>
  <material>
   Кожа
  </material>
  <price>
   416349
  </price>
  <rating>
   1.6
  </rating>
  <reviews>
   379346
  </reviews>
  <new>
   +
  </new>
  <exclusive>
   yes
  </exclusive>
  <sporty>
   no
  </sporty>
 </clothing>
 <clothing>
  <id>
   720022554
  </id>
  <name>
   Fila Pants D-3792
  </name>
  <category>
   Pants
  </category>
  <size>
   L
  </size>
  <color>
   Фиолетовый
  </color>
  <material>
   Вискоза
  </material>
  <price>
   387319
  </price>
  <rating>
   3.1
  </rating>
  <reviews>
   969882
  </reviews>
  <new>
   -
  </new>
  <sporty>
   no
  </sporty>
 </clothing>
 <clothing>
  <id>
   316227412
  </id>
  <name>
   Ellesse Socks I-4904
  </name>
  <category>
   Socks
  </category>
  <size>
   L
  </size>
  <color>
   Голубой
  </color>
  <material>
   Лен
  </material>
  <price>
   180107
  </price>
  <rating>
   3.36
  </rating>
  <reviews>
   467087
  </reviews>
  <new>
   +
  </new>
 </clothing>
 <clothing>
  <id>
   618546567
  </id>
  <name>
   PleinSport Socks C-5408
  </name>
  <category>
   Socks
  </category>
  <size>
   XXL
  </size>
  <color>
   Оранжевый
  </color>
  <material>
   Лен
  </material>
  <price>
   788093
  </price>
  <rating>
   4.07
  </rating>
  <reviews>
   157613
  </reviews>
  <new>
   -
  </new>
  <exclusive>
   no
  </exclusive>
  <sporty>
   yes
  </sporty>
 </clothing>
 <clothing>
  <id>
   864657346
  </id>
  <name>
   Vans Shirt B-6900
  </name>
  <category>
   Shirt
  </category>
  <size>
   XXL
  </size>
  <color>
   Фиолетовый
  </color>
  <material>
   Кожа
  </material>
  <price>
   889111
  </price>
  <rating>
   2.7
  </rating>
  <reviews>
   364703
  </reviews>
  <exclusive>
   yes
  </exclusive>
 </clothing>
 <clothing>
  <id>
   637670027
  </id>
  <name>
   Nike Socks Q-5201
  </name>
  <category>
   Socks
  </category>
  <size>
   S
  </size>
  <color>
   Красный
  </color>
  <material>
   Шелк
  </material>
  <price>
   930232
  </price>
  <rating>
   3.73
  </rating>
  <reviews>
   542881
  </reviews>
  <new>
   +
  </new>
  <sporty>
   no
  </sporty>
 </clothing>
 <clothing>
  <id>
   510779360
  </id>
  <name>
   Under Armour Gloves W-9300
  </name>
  <category>
   Gloves
  </category>
  <size>
   XL
  </size>
  <color>
   Фиолетовый
  </color>
  <material>
   Вискоза
  </material>
  <price>
   439430
  </price>
  <rating>
   2.86
  </rating>
  <reviews>
   775337
  </reviews>
  <new>
   -
  </new>
  <sporty>
   no
  </sporty>
 </clothing>
 <clothing>
  <id>
   197631691
  </id>
  <name>
   Puma Shoes K-6074
  </name>
  <category>
   Shoes
  </category>
  <size>
   L
  </size>
  <color>
   Красный
  </color>
  <material>
   Вискоза
  </material>
  <price>
   484413
  </price>
  <rating>
   1.1
  </rating>
  <reviews>
   950238
  </reviews>
  <new>
   -
  </new>
 </clothing>
 <clothing>
  <id>
   296022176
  </id>
  <name>
   Lacoste Shoes G-9202
  </name>
  <category>
   Shoes
  </category>
  <size>
   S
  </size>
  <color>
   Фиолетовый
  </color>
  <material>
   Нейлон
  </material>
  <price>
   393805
  </price>
  <rating>
   2.46
  </rating>
  <reviews>
   462101
  </reviews>
 </clothing>
 <clothing>
  <id>
   729668058
  </id>
  <name>
   Addidas Dress V-5192
  </name>
  <category>
   Dress
  </category>
  <size>
   XXL
  </size>
  <color>
   Голубой
  </color>
  <material>
   Нейлон
  </material>
  <price>
   505085
  </price>
  <rating>
   4.12
  </rating>
  <reviews>
   284113
  </reviews>
  <new>
   -
  </new>
  <exclusive>
   no
  </exclusive>
 </clothing>
 <clothing>
  <id>
   939578665
  </id>
  <name>
   Ellesse Socks C-1411
  </name>
  <category>
   Socks
  </category>
  <size>
   XL
  </size>
  <color>
   Желтый
  </color>
  <material>
   Лен
  </material>
  <price>
   709319
  </price>
  <rating>
   2.84
  </rating>
  <reviews>
   370800
  </reviews>
  <new>
   +
  </new>
 </clothing>
 <clothing>
  <id>
   313652811
  </id>
  <name>
   DC Shirt E-8022
  </name>
  <category>
   Shirt
  </category>
  <size>
   XL
  </size>
  <color>
   Красный
  </color>
  <material>
   Шелк
  </material>
  <price>
   247014
  </price>
  <rating>
   1.56
  </rating>
  <reviews>
   785040
  </reviews>
  <new>
   +
  </new>
  <sporty>
   yes
  </sporty>
 </clothing>
 <clothing>
  <id>
   624611388
  </id>
  <name>
   Puma T-shirt D-8841
  </name>
  <category>
   T-shirt
  </category>
  <size>
   XXL
  </size>
  <color>
   Фиолетовый
  </color>
  <material>
   Шерсть
  </material>
  <price>
   921093
  </price>
  <rating>
   3.47
  </rating>
  <reviews>
   926454
  </reviews>
 </clothing>
 <clothing>
  <id>
   928736039
  </id>
  <name>
   Asics Shoes B-4633
  </name>
  <category>
   Shoes
  </category>
  <size>
   S
  </size>
  <color>
   Красный
  </color>
  <material>
   Хлопок
  </material>
  <price>
   738528
  </price>
  <rating>
   3.33
  </rating>
  <reviews>
   779031
  </reviews>
  <new>
   -
  </new>
 </clothing>
 <clothing>
  <id>
   836793098
  </id>
  <name>
   Brooks Dress Y-7763
  </name>
  <category>
   Dress
  </category>
  <size>
   XL
  </size>
  <color>
   Голубой
  </color>
  <material>
   Хлопок
  </material>
  <price>
   371491
  </price>
  <rating>
   3.7
  </rating>
  <reviews>
   39430
  </reviews>
  <exclusive>
   yes
  </exclusive>
  <sporty>
   no
  </sporty>
 </clothing>
 <clothing>
  <id>
   600758029
  </id>
  <name>
   Ellesse Socks B-7374
  </name>
  <category>
   Socks
  </category>
  <size>
   L
  </size>
  <color>
   Фиолетовый
  </color>
  <material>
   Нейлон
  </material>
  <price>
   982810
  </price>
  <rating>
   4.17
  </rating>
  <reviews>
   889847
  </reviews>
  <new>
   -
  </new>
  <exclusive>
   no
  </exclusive>
 </clothing>
 <clothing>
  <id>
   707818709
  </id>
  <name>
   Lacoste Jacket I-6174
  </name>
  <category>
   Jacket
  </category>
  <size>
   XL
  </size>
  <color>
   Синий
  </color>
  <material>
   Полиэстер
  </material>
  <price>
   489931
  </price>
  <rating>
   3.01
  </rating>
  <reviews>
   677927
  </reviews>
  <exclusive>
   no
  </exclusive>
 </clothing>
 <clothing>
  <id>
   172911586
  </id>
  <name>
   Converse T-shirt D-3302
  </name>
  <category>
   T-shirt
  </category>
  <size>
   S
  </size>
  <color>
   Фиолетовый
  </color>
  <material>
   Вискоза
  </material>
  <price>
   356803
  </price>
  <rating>
   3.59
  </rating>
  <reviews>
   557267
  </reviews>
  <sporty>
   yes
  </sporty>
 </clothing>
 <clothing>
  <id>
   811077767
  </id>
  <name>
   Addidas T-shirt K-9483
  </name>
  <category>
   T-shirt
  </category>
  <size>
   S
  </size>
  <color>
   Голубой
  </color>
  <material>
   Кожа
  </material>
  <price>
   430421
  </price>
  <rating>
   3.08
  </rating>
  <reviews>
   33322
  </reviews>
  <new>
   +
  </new>
  <exclusive>
   no
  </exclusive>
 </clothing>
 <clothing>
  <id>
   194919037
  </id>
  <name>
   Lacoste Skirt G-9344
  </name>
  <category>
   Skirt
  </category>
  <size>
   M
  </size>
  <color>
   Зеленый
  </color>
  <material>
   Лен
  </material>
  <price>
   467719
  </price>
  <rating>
   3.23
  </rating>
  <reviews>
   805923
  </reviews>
  <new>
   -
  </new>
  <sporty>
   no
  </sporty>
 </clothing>
 <clothing>
  <id>
   649627150
  </id>
  <name>
   DC Handbags X-7093
  </name>
  <category>
   Handbags
  </category>
  <size>
   S
  </size>
  <color>
   Оранжевый
  </color>
  <material>
   Вискоза
  </material>
  <price>
   340770
  </price>
  <rating>
   2.0
  </rating>
  <reviews>
   962573
  </reviews>
  <new>
   -
  </new>
  <sporty>
   yes
  </sporty>
 </clothing>
 <clothing>
  <id>
   836224702
  </id>
  <name>
   Puma Belts C-2741
  </name>
  <category>
   Belts
  </category>
  <size>
   XXL
  </size>
  <color>
   Фиолетовый
  </color>
  <material>
   Полиэстер
  </material>
  <price>
   680849
  </price>
  <rating>
   4.7
  </rating>
  <reviews>
   444795
  </reviews>
  <new>
   +
  </new>
  <sporty>
   yes
  </sporty>
 </clothing>
 <clothing>
  <id>
   468564483
  </id>
  <name>
   Addidas Socks Y-9891
  </name>
  <category>
   Socks
  </category>
  <size>
   L
  </size>
  <color>
   Голубой
  </color>
  <material>
   Кожа
  </material>
  <price>
   446147
  </price>
  <rating>
   4.64
  </rating>
  <reviews>
   809638
  </reviews>
  <exclusive>
   no
  </exclusive>
  <sporty>
   no
  </sporty>
 </clothing>
 <clothing>
  <id>
   348582690
  </id>
  <name>
   Reebok Handbags V-9492
  </name>
  <category>
   Handbags
  </category>
  <size>
   S
  </size>
  <color>
   Оранжевый
  </color>
  <material>
   Хлопок
  </material>
  <price>
   307895
  </price>
  <rating>
   2.75
  </rating>
  <reviews>
   609332
  </reviews>
  <exclusive>
   no
  </exclusive>
  <sporty>
   no
  </sporty>
 </clothing>
 <clothing>
  <id>
   370241277
  </id>
  <name>
   Asics Handbags X-6199
  </name>
  <category>
   Handbags
  </category>
  <size>
   S
  </size>
  <color>
   Голубой
  </color>
  <material>
   Вискоза
  </material>
  <price>
   497594
  </price>
  <rating>
   3.97
  </rating>
  <reviews>
   333776
  </reviews>
  <sporty>
   yes
  </sporty>
 </clothing>
 <clothing>
  <id>
   740315934
  </id>
  <name>
   Puma Sweater X-9329
  </name>
  <category>
   Sweater
  </category>
  <size>
   M
  </size>
  <color>
   Синий
  </color>
  <material>
   Кожа
  </material>
  <price>
   666097
  </price>
  <rating>
   3.63
  </rating>
  <reviews>
   764276
  </reviews>
  <sporty>
   yes
  </sporty>
 </clothing>
 <clothing>
  <id>
   756020934
  </id>
  <name>
   PleinSport Pants P-6085
  </name>
  <category>
   Pants
  </category>
  <size>
   L
  </size>
  <color>
   Голубой
  </color>
  <material>
   Шерсть
  </material>
  <price>
   865263
  </price>
  <rating>
   3.93
  </rating>
  <reviews>
   73799
  </reviews>
  <new>
   +
  </new>
 </clothing>
 <clothing>
  <id>
   212448553
  </id>
  <name>
   Adidas Shoes O-1848
  </name>
  <category>
   Shoes
  </category>
  <size>
   XXL
  </size>
  <color>
   Голубой
  </color>
  <material>
   Шерсть
  </material>
  <price>
   878518
  </price>
  <rating>
   3.78
  </rating>
  <reviews>
   529011
  </reviews>
  <sporty>
   no
  </sporty>
 </clothing>
 <clothing>
  <id>
   400052981
  </id>
  <name>
   Brooks Shoes U-4326
  </name>
  <category>
   Shoes
  </category>
  <size>
   XL
  </size>
  <color>
   Красный
  </color>
  <material>
   Нейлон
  </material>
  <price>
   527849
  </price>
  <rating>
   2.19
  </rating>
  <reviews>
   852088
  </reviews>
  <new>
   -
  </new>
  <exclusive>
   no
  </exclusive>
  <sporty>
   yes
  </sporty>
 </clothing>
 <clothing>
  <id>
   896675264
  </id>
  <name>
   Converse Blouse G-4575
  </name>
  <category>
   Blouse
  </category>
  <size>
   M
  </size>
  <color>
   Зеленый
  </color>
  <material>
   Шелк
  </material>
  <price>
   926511
  </price>
  <rating>
   1.85
  </rating>
  <reviews>
   780780
  </reviews>
  <exclusive>
   yes
  </exclusive>
 </clothing>
</clothing-items>
